{"lastUpdate": "2011-12-06 12:54", "data": {"LIP-Lisbon(ES)": {"JobDef": 180, "Jobs": 7220}, "INFN-MILANO-ATLASC(IT)": {"JobDef": 3061, "Jobs": 77521}, "UKI-SCOTGRID-ECDF(UK)": {"JobDef": 1352, "Jobs": 30009}, "UKI-LT2-UCL-HEP(UK)": {"JobDef": 1173, "Jobs": 22987}, "CSCS-LCG2(DE)": {"JobDef": 3291, "Jobs": 79168}, "SARA-MATRIX(NL)": {"JobDef": 1370, "Jobs": 337547}, "CA-MCGILL-CLUMEQ-T2(CA)": {"JobDef": 458, "Jobs": 15095}, "UKI-NORTHGRID-LIV-HEP(UK)": {"JobDef": 2807, "Jobs": 45580}, "CA-ALBERTA-WESTGRID-T2(CA)": {"JobDef": 1861, "Jobs": 36696}, "UKI-NORTHGRID-LANCS-HEP(UK)": {"JobDef": 5534, "Jobs": 120067}, "NDGF-T1(ND)": {"JobDef": 5936, "Jobs": 163580}, "ifae(ES)": {"JobDef": 1038, "Jobs": 39668}, "wuppertalprod(DE)": {"JobDef": 4680, "Jobs": 113538}, "RO-07-NIPNE(FR)": {"JobDef": 1135, "Jobs": 25862}, "TOKYO-LCG2(FR)": {"JobDef": 5488, "Jobs": 210699}, "UKI-SOUTHGRID-CAM-HEP(UK)": {"JobDef": 276, "Jobs": 6833}, "UKI-SOUTHGRID-OX-HEP(UK)": {"JobDef": 3180, "Jobs": 82307}, "WT2(US)": {"JobDef": 4851, "Jobs": 157272}, "TW-FTT(TW)": {"JobDef": 1220, "Jobs": 166494}, "UKI-LT2-QMUL(UK)": {"JobDef": 6611, "Jobs": 225802}, "NIKHEF-ELPROD(NL)": {"JobDef": 8759, "Jobs": 200250}, "IN2P3-CC(FR)": {"JobDef": 5171, "Jobs": 207913}, "WEIZMANN-LCG2(NL)": {"JobDef": 1435, "Jobs": 32086}, "TECHNION-HEP(NL)": {"JobDef": 1702, "Jobs": 36716}, "IN2P3-LPC(FR)": {"JobDef": 1808, "Jobs": 59434}, "IN2P3-LPSC(FR)": {"JobDef": 730, "Jobs": 20328}, "UKI-NORTHGRID-MAN-HEP(UK)": {"JobDef": 2660, "Jobs": 88393}, "LIP-Coimbra(ES)": {"JobDef": 286, "Jobs": 4708}, "Australia-ATLAS(CA)": {"JobDef": 2528, "Jobs": 51510}, "MWT2_UC(US)": {"JobDef": 8687, "Jobs": 241562}, "IN2P3-CPPM(FR)": {"JobDef": 2111, "Jobs": 42605}, "AGLT2(US)": {"JobDef": 7876, "Jobs": 255456}, "RO-02-NIPNE(FR)": {"JobDef": 199, "Jobs": 3235}, "HEPHY-UIBK(DE)": {"JobDef": 163, "Jobs": 6781}, "INFN-FRASCATI(IT)": {"JobDef": 700, "Jobs": 14508}, "GoeGrid(DE)": {"JobDef": 2386, "Jobs": 43269}, "BU_ATLAS_Tier2(US)": {"JobDef": 5159, "Jobs": 128902}, "IL-TAU-HEP(NL)": {"JobDef": 298, "Jobs": 2948}, "IllinoisHEP(US)": {"JobDef": 1202, "Jobs": 23640}, "JINR-LCG2(NL)": {"JobDef": 1003, "Jobs": 32473}, "INFN-ROMA1(IT)": {"JobDef": 3736, "Jobs": 74894}, "RRC-KI(NL)": {"JobDef": 1, "Jobs": 3}, "INFN-NAPOLI-ATLAS(IT)": {"JobDef": 6069, "Jobs": 122729}, "RAL-LCG2(UK)": {"JobDef": 5038, "Jobs": 344455}, "BEIJING-LCG2(FR)": {"JobDef": 2204, "Jobs": 38781}, "UKI-SCOTGRID-GLASGOW(UK)": {"JobDef": 5143, "Jobs": 151405}, "FZK-LCG2(DE)": {"JobDef": 2568, "Jobs": 148262}, "CA-SCINET-T2(CA)": {"JobDef": 4169, "Jobs": 103458}, "CERN-PROD(CERN)": {"JobDef": 3760, "Jobs": 235712}, "GRIF-LPNHE(FR)": {"JobDef": 4160, "Jobs": 115745}, "INFN-BOLOGNA-T3(IT)": {"JobDef": 487, "Jobs": 6458}, "GRIF-LAL(FR)": {"JobDef": 1233, "Jobs": 32158}, "TUDresden-ZIH(DE)": {"JobDef": 70, "Jobs": 1924}, "CA-VICTORIA-WESTGRID-T2(CA)": {"JobDef": 3538, "Jobs": 88117}, "praguelcg2(DE)": {"JobDef": 3041, "Jobs": 105045}, "BNL-ATLAS(US)": {"JobDef": 25921, "Jobs": 890905}, "DESY-ZN(DE)": {"JobDef": 5912, "Jobs": 181255}, "GRIF-IRFU(FR)": {"JobDef": 165, "Jobs": 5722}, "UTA_SWT2(US)": {"JobDef": 3953, "Jobs": 145950}, "UKI-SOUTHGRID-RALPP(UK)": {"JobDef": 1070, "Jobs": 27543}, "MPPMU(DE)": {"JobDef": 640, "Jobs": 15569}, "IFIC-LCG2(ES)": {"JobDef": 3272, "Jobs": 72639}, "LRZ-LMU(DE)": {"JobDef": 5776, "Jobs": 151410}, "UKI-LT2-RHUL(UK)": {"JobDef": 6093, "Jobs": 100779}, "OU_OCHEP_SWT2(US)": {"JobDef": 1607, "Jobs": 13309}, "UKI-SOUTHGRID-BHAM-HEP(UK)": {"JobDef": 628, "Jobs": 17313}, "SFU-LCG2(CA)": {"JobDef": 2993, "Jobs": 79398}, "pic(ES)": {"JobDef": 683, "Jobs": 39367}, "DESY-HH(DE)": {"JobDef": 8061, "Jobs": 142810}, "INFN-GENOVA(IT)": {"JobDef": 387, "Jobs": 6390}, "IN2P3-CC-T2(FR)": {"JobDef": 4609, "Jobs": 164800}, "NCG-INGRID-PT(ES)": {"JobDef": 444, "Jobs": 8732}, "TRIUMF-LCG2(CA)": {"JobDef": 2830, "Jobs": 105242}, "INFN-T1(IT)": {"JobDef": 2613, "Jobs": 119650}, "IN2P3-LAPP(FR)": {"JobDef": 3656, "Jobs": 80687}, "CYFRONET-LCG2(DE)": {"JobDef": 3350, "Jobs": 95959}, "TR-10-ULAKBIM(NL)": {"JobDef": 617, "Jobs": 13530}, "UKI-NORTHGRID-SHEF-HEP(UK)": {"JobDef": 3566, "Jobs": 59016}, "UNI-FREIBURG(DE)": {"JobDef": 4178, "Jobs": 140575}, "RU-Protvino-IHEP(NL)": {"JobDef": 1591, "Jobs": 35590}}, "columns": {"field2": {"type": "number", "name": "JobDef"}, "field0": {"type": "string", "name": "Site"}, "field1": {"type": "number", "name": "Jobs"}}}